monitor_internet_connection/__init__.py
monitor_internet_connection/__main__.py
monitor_internet_connection/monitor_internet_connection.py
monitor_internet_connection-1.2.1.dist-info/LICENSE.md
monitor_internet_connection-1.2.1.dist-info/METADATA
monitor_internet_connection-1.2.1.dist-info/WHEEL
monitor_internet_connection-1.2.1.dist-info/top_level.txt
monitor_internet_connection-1.2.1.dist-info/RECORD
