Metadata-Version: 2.1
Name: monitor-internet-connection
Version: 1.2.1
Summary: A Python module to monitor the uptime of the Internet connection and record the time and duration of any downtime
Home-page: https://github.com/mfoc/monitor-internet-connection
Author: Martin Francis O'Connor
Author-email: cslearncreate@gmail.com
License: UNKNOWN
Platform: UNKNOWN
Classifier: Programming Language :: Python :: 3
Classifier: License :: OSI Approved :: MIT License
Classifier: Operating System :: OS Independent
Requires-Python: >=3.6
